odoo/addons/hr_expense_sequence_option/README.rst
odoo/addons/hr_expense_sequence_option/__init__.py
odoo/addons/hr_expense_sequence_option/__manifest__.py
odoo/addons/hr_expense_sequence_option/demo/hr_expense_demo_options.xml
odoo/addons/hr_expense_sequence_option/i18n/es.po
odoo/addons/hr_expense_sequence_option/i18n/hr_expense_sequence_option.pot
odoo/addons/hr_expense_sequence_option/i18n/it.po
odoo/addons/hr_expense_sequence_option/models/__init__.py
odoo/addons/hr_expense_sequence_option/models/hr_expense_sheet.py
odoo/addons/hr_expense_sequence_option/models/sequence_option.py
odoo/addons/hr_expense_sequence_option/readme/CONTRIBUTORS.rst
odoo/addons/hr_expense_sequence_option/readme/DESCRIPTION.rst
odoo/addons/hr_expense_sequence_option/static/description/icon.png
odoo/addons/hr_expense_sequence_option/static/description/index.html
odoo/addons/hr_expense_sequence_option/tests/__init__.py
odoo/addons/hr_expense_sequence_option/tests/test_hr_expense_sequence_option.py
odoo14_addon_hr_expense_sequence_option-14.0.1.0.1.dev10.dist-info/METADATA
odoo14_addon_hr_expense_sequence_option-14.0.1.0.1.dev10.dist-info/WHEEL
odoo14_addon_hr_expense_sequence_option-14.0.1.0.1.dev10.dist-info/top_level.txt
odoo14_addon_hr_expense_sequence_option-14.0.1.0.1.dev10.dist-info/RECORD
